napari_meshio/__init__.py
napari_meshio/_available_file_formats.py
napari_meshio/_reader.py
napari_meshio/_sample_data.py
napari_meshio/_version.py
napari_meshio/_writer.py
napari_meshio/napari.yaml
napari_meshio/_tests/__init__.py
napari_meshio/_tests/test_reader.py
napari_meshio/_tests/test_sample_data.py
napari_meshio/_tests/test_writer.py
napari_meshio-0.0.2.dist-info/licenses/LICENSE
napari_meshio-0.0.2.dist-info/METADATA
napari_meshio-0.0.2.dist-info/WHEEL
napari_meshio-0.0.2.dist-info/entry_points.txt
napari_meshio-0.0.2.dist-info/top_level.txt
napari_meshio-0.0.2.dist-info/RECORD
