Metadata-Version: 2.4
Name: napari-meshio
Version: 0.0.2
Summary: I/O for mesh files.
Home-page: https://github.com/GenevieveBuckley/napari-meshio
Author: Genevieve Buckley
Author-email: yourname@example.com
License: MIT
Project-URL: Bug Tracker, https://github.com/GenevieveBuckley/napari-meshio/issues
Project-URL: Documentation, https://github.com/GenevieveBuckley/napari-meshio#README.md
Project-URL: Source Code, https://github.com/GenevieveBuckley/napari-meshio
Project-URL: User Support, https://github.com/GenevieveBuckley/napari-meshio/issues
Classifier: Development Status :: 2 - Pre-Alpha
Classifier: Framework :: napari
Classifier: Intended Audience :: Developers
Classifier: License :: OSI Approved :: MIT License
Classifier: Operating System :: OS Independent
Classifier: Programming Language :: Python
Classifier: Programming Language :: Python :: 3
Classifier: Programming Language :: Python :: 3 :: Only
Classifier: Programming Language :: Python :: 3.8
Classifier: Programming Language :: Python :: 3.9
Classifier: Programming Language :: Python :: 3.10
Classifier: Topic :: Scientific/Engineering :: Image Processing
Requires-Python: >=3.8
License-File: LICENSE
Requires-Dist: numpy
Requires-Dist: meshio
Requires-Dist: pooch
Requires-Dist: rich
Provides-Extra: testing
Requires-Dist: mkdocs; extra == "testing"
Requires-Dist: mkdocs-gen-files; extra == "testing"
Requires-Dist: napari; extra == "testing"
Requires-Dist: tox; extra == "testing"
Requires-Dist: pytest; extra == "testing"
Requires-Dist: pytest-cov; extra == "testing"
Requires-Dist: pyvista; extra == "testing"
Dynamic: license-file
